odoo10_addon_account_type_menu-10.0.1.0.0.99.dev5-py2.7-nspkg.pth
odoo/addons/account_type_menu/README.rst
odoo/addons/account_type_menu/__init__.py
odoo/addons/account_type_menu/__manifest__.py
odoo/addons/account_type_menu/i18n/account_type_menu.pot
odoo/addons/account_type_menu/i18n/hr.po
odoo/addons/account_type_menu/i18n/tr.po
odoo/addons/account_type_menu/static/description/icon.png
odoo/addons/account_type_menu/views/account_type.xml
odoo10_addon_account_type_menu-10.0.1.0.0.99.dev5.dist-info/METADATA
odoo10_addon_account_type_menu-10.0.1.0.0.99.dev5.dist-info/RECORD
odoo10_addon_account_type_menu-10.0.1.0.0.99.dev5.dist-info/WHEEL
odoo10_addon_account_type_menu-10.0.1.0.0.99.dev5.dist-info/namespace_packages.txt
odoo10_addon_account_type_menu-10.0.1.0.0.99.dev5.dist-info/top_level.txt
